roboid/__init__.py
roboid/albert_ai.py
roboid/albert_ai_roboid.py
roboid/beagle.py
roboid/beagle_roboid.py
roboid/connector.py
roboid/grid.py
roboid/hamster.py
roboid/hamster_roboid.py
roboid/hamster_s.py
roboid/hamster_s_roboid.py
roboid/keyboard.py
roboid/model.py
roboid/pio.py
roboid/pio_roboid.py
roboid/raccoon.py
roboid/raccoon_roboid.py
roboid/runner.py
roboid/scanner.py
roboid/serial_connector.py
roboid/serial_queue.py
roboid/turtle.py
roboid/turtle_roboid.py
roboid/util.py
roboid/zerone.py
roboid/zerone_roboid.py
roboid-1.7.3.dist-info/LICENSE
roboid-1.7.3.dist-info/METADATA
roboid-1.7.3.dist-info/WHEEL
roboid-1.7.3.dist-info/top_level.txt
roboid-1.7.3.dist-info/RECORD
