Metadata-Version: 2.1
Name: roboid
Version: 1.7.3
Summary: Python Package for Hamster, Hamster-S, Turtle, Albert Ai, Zerone, and Beagle
Author: Kwang-Hyun Park
Author-email: akaii@kw.ac.kr
Classifier: License :: OSI Approved :: GNU Lesser General Public License v2 or later (LGPLv2+)
Requires-Python: >=3
License-File: LICENSE
Requires-Dist: pyserial
